<?xml version="1.0" encoding="iso-8859-9" ?>
<item>
<eklenti_adi>Ana Sayfa</eklenti_adi>
<aspcode><![CDATA[

Response.Write "<title>"&siteadi&"</title>"

SQLmod ="SELECT * from gop_modules where modul_izin = '"& 1 &"' AND modul_yer ='orta_ust' order by modul_sira asc;"
set modul = server.createobject("ADODB.Recordset")
modul.open SQLmod , Baglanti
if modul.eof or modul.bof then 
Response.write ""
else

do while not modul.eof

Execute modul("modul_icerik")


modul.MoveNext
loop
modul.close
set modul=nothing
end if


set son_veri = baglanti.Execute("select * from gop_veriler where vgoster ='"& 1 &"' order by vid DESC")

Response.Write "<table width=""100%"" border=""0"" cellspacing=""0"" cellpadding=""0""><tr>"

if kresimg = 1 then
Response.Write "<td width=100><img src="& son_veri("vresim") &" height=""75"" width=""100"" align=""left"" onerror=""this.src='images/joomlasp.jpg'"" align=left height=75 width=100></td>"
end if

Response.Write "<td><strong><a href=""default.asp?islem=oku&vid="&son_veri("vid")&""">" &son_veri("vbaslik") & "</a></strong><br>"&left(son_veri("vicerik"),500)&"...</td></tr><tr><td></td><td align=""right""> <br>"&hit&": "&son_veri("vhit")&"</td></tr><tr><td></td><td align=""right""><a href=""default.asp?islem=oku&vid="&son_veri("vid")&""">"&read_more&"</a></td></tr></table><br><br>"
son_veri.close
set son_veri=nothing


SQLmod ="SELECT * from gop_modules where modul_izin = '"& 1 &"' AND modul_yer ='orta_orta' order by modul_sira asc;"
set modul = server.createobject("ADODB.Recordset")
modul.open SQLmod , Baglanti
if modul.eof or modul.bof then 
Response.write ""
else

do while not modul.eof

Execute modul("modul_icerik")


modul.MoveNext
loop
modul.close
set modul=nothing
end if

Response.Write "<table width=""100%"" border=""0"" cellpadding=""0"" cellspacing=""10""><tr align=""left"">"

deste = vsayi
If Request.QueryString("s") <> "" Then 
  Sayfa = CInt(Request.QueryString("s"))
Else 
  Sayfa = 1 
End If 

set veri = baglanti.Execute("select * from gop_veriler where vgoster ='"& 1 &"' order by vid DESC LIMIT "& (deste*Sayfa)-(deste)+1 & "," & deste)

Set SQLToplam = baglanti.Execute("select count(vid) from gop_veriler where vgoster ='"& 1 &"'") 
TopKayit = SQLToplam(0)


for z=1 to 10
if  veri.eof then exit for

Response.Write "<td width=""50%"" valign=""top"">"

if kresimg = 1 then
Response.Write "<img src="& veri("vresim") &" height=""75"" width=""100"" align=""left"" onerror=""this.src='images/joomlasp.jpg'"" align=left height=75 width=100>"
end if


Response.Write "<b><a href=default.asp?islem=oku&vid="&veri("vid")&">" & veri("vbaslik") & "...</a></b><br>"&left(veri("vicerik"),vkarakter)&"..."

Response.Write "<p align=""right""><a href=default.asp?islem=oku&vid="&veri("vid")&">"&read_more&"</a><br>"&hit&": "&veri("vhit")&"</p></td>"
if z mod vsutun = 0 then response.write "</tr><tr>"

veri.MoveNext
next
veri.close
set veri=nothing

Response.Write "</tr></table><div align=""center"">"

If CInt(TopKayit) > CInt(deste) Then 
SayfaSayisi = CInt(TopKayit) / CInt(deste) 
If InStr(1,SayfaSayisi,",",1) > 1 Then SayfaSayisi = CInt(Left(SayfaSayisi,InStr(1,SayfaSayisi,",",1))) + 1 

If SayfaSayisi > 1 Then 
Response.Write "<a class=pagenav href=?vid="&vid&"&s=1><< "&start_page&"</a> "
if Sayfa = 1 then
Response.Write ""
else
Response.Write "<a class=pagenav href=?vid="&vid&"&s="&Sayfa-1&">< "&prev_page&"</a> "
end if

for t=d to Sayfa-1
if Sayfa > Sayfa-5 and t > Sayfa-5  and t > 0 then
Response.Write " <a class=pagenav href=?vid="&vid&"&s=" & t & "><b>" & t & "</b></a> "
end if
next 

For d=Sayfa To Sayfa+4
if d = CInt(Sayfa) then
Response.Write "<span class=pagenav><b>" & d & "</b></span>"
elseif d > SayfaSayisi then
Response.Write ""
else
Response.Write " <a class=pagenav href=?vid="&vid&"&s=" & d & "><b>" & d & "</b></a> " 
end if
Next


if Sayfa = SayfaSayisi then
Response.Write ""
else
Response.Write " <a class=pagenav href=?s="&Sayfa+1&"> "&next_page&" ></a> "
Response.Write " <a class=pagenav href=?s="&SayfaSayisi&">"&end_page&" >></a>"
end if


End If 
End If 

Response.Write "</div>"

SQLmod ="SELECT * from gop_modules where modul_izin = '"& 1 &"' AND modul_yer ='orta_alt' order by modul_sira asc;"
set modul = server.createobject("ADODB.Recordset")
modul.open SQLmod , Baglanti
if modul.eof or modul.bof then 
Response.write " "
else

do while not modul.eof

Execute modul("modul_icerik")


modul.MoveNext
loop
modul.close
set modul=nothing
end if

]]></aspcode>
<eklenti_yazar>JoomlASP</eklenti_yazar>
<eklenti_k>main_page</eklenti_k>
<eklenti_mail>info@joomlasp.com</eklenti_mail>
<eklenti_web>info@joomlasp.com</eklenti_web>
</item>